{
    "description": "CC Invoice Approval Process",
    "display_name": "CCC Invoice Approval Process",
    "display_order": 0,
    "exception_notification_addresses": [],
    "fault_or_suspend_on_exception": "fault",
    "files": [],
    "id": "cc-invoice-approval-process",
    "is_master_spec": false,
    "is_review": true,
    "libraries": [],
    "library": false,
    "primary_file_name": "cc-invoice-approval-process-v2.bpmn",
    "primary_process_id": "Process_cc_invoice_approval_process_v2_a",
    "process_group_id": "execute-procure-to-pay",
    "standalone": false
}